agentready/__init__.py
agentready/assessors/__init__.py
agentready/assessors/base.py
agentready/assessors/code_quality.py
agentready/assessors/containers.py
agentready/assessors/documentation.py
agentready/assessors/repomix.py
agentready/assessors/security.py
agentready/assessors/structure.py
agentready/assessors/stub_assessors.py
agentready/assessors/testing.py
agentready/cli/__init__.py
agentready/cli/align.py
agentready/cli/assess_batch.py
agentready/cli/benchmark.py
agentready/cli/bootstrap.py
agentready/cli/demo.py
agentready/cli/eval_harness.py
agentready/cli/experiment.py
agentready/cli/extract_skills.py
agentready/cli/harbor.py
agentready/cli/learn.py
agentready/cli/main.py
agentready/cli/main_simplified.py
agentready/cli/repomix.py
agentready/cli/research.py
agentready/cli/schema.py
agentready/cli/submit.py
agentready/data/RESEARCH_REPORT.md
agentready/data/default-weights.yaml
agentready/fixers/__init__.py
agentready/fixers/base.py
agentready/fixers/documentation.py
agentready/fixers/testing.py
agentready/github/__init__.py
agentready/github/review_formatter.py
agentready/learners/__init__.py
agentready/learners/code_sampler.py
agentready/learners/llm_enricher.py
agentready/learners/pattern_extractor.py
agentready/learners/prompt_templates.py
agentready/learners/skill_generator.py
agentready/models/__init__.py
agentready/models/assessment.py
agentready/models/attribute.py
agentready/models/batch_assessment.py
agentready/models/citation.py
agentready/models/config.py
agentready/models/discovered_skill.py
agentready/models/eval_harness.py
agentready/models/finding.py
agentready/models/fix.py
agentready/models/harbor.py
agentready/models/metadata.py
agentready/models/repository.py
agentready/models/theme.py
agentready/reporters/__init__.py
agentready/reporters/aggregated_json.py
agentready/reporters/base.py
agentready/reporters/csv_reporter.py
agentready/reporters/harbor_markdown.py
agentready/reporters/html.py
agentready/reporters/json_reporter.py
agentready-2.24.1.dist-info/licenses/LICENSE
agentready-2.24.1.dist-info/METADATA
agentready-2.24.1.dist-info/WHEEL
agentready-2.24.1.dist-info/entry_points.txt
agentready-2.24.1.dist-info/top_level.txt
agentready-2.24.1.dist-info/RECORD
