Metadata-Version: 2.4
Name: agentready
Version: 2.24.1
Summary: Assess and bootstrap git repositories for AI-assisted development with automated remediation and continuous learning
Author-email: Jeremy Eder <jeder@redhat.com>
License: MIT
Classifier: Development Status :: 4 - Beta
Classifier: Intended Audience :: Developers
Classifier: License :: OSI Approved :: MIT License
Classifier: Programming Language :: Python :: 3.12
Classifier: Programming Language :: Python :: 3.13
Classifier: Topic :: Software Development :: Quality Assurance
Requires-Python: >=3.12
License-File: LICENSE
Requires-Dist: click>=8.1.0
Requires-Dist: jinja2>=3.1.0
Requires-Dist: pyyaml>=6.0
Requires-Dist: gitpython>=3.1.0
Requires-Dist: radon>=6.0.0
Requires-Dist: lizard>=1.17.0
Requires-Dist: anthropic>=0.74.0
Requires-Dist: jsonschema>=4.17.0
Requires-Dist: requests>=2.31.0
Requires-Dist: pydantic>=2.0.0
Requires-Dist: pandas>=2.0.0
Requires-Dist: plotly>=5.0.0
Requires-Dist: scipy>=1.10.0
Requires-Dist: PyGithub>=2.1.1
Provides-Extra: dev
Requires-Dist: pytest>=7.4.0; extra == "dev"
Requires-Dist: pytest-cov>=4.1.0; extra == "dev"
Requires-Dist: black>=23.0.0; extra == "dev"
Requires-Dist: isort>=5.12.0; extra == "dev"
Requires-Dist: flake8>=6.0.0; extra == "dev"
Requires-Dist: ruff>=0.1.0; extra == "dev"
Dynamic: license-file
